app/__init__.py
app/accounts.py
app/blocks.py
app/contracts.py
app/conversions.py
app/etherchainpy.py
app/geth.py
app/logs.py
app/transactions.py
etherchainpy/__init__.py
etherchainpy/accounts.py
etherchainpy/blocks.py
etherchainpy/contracts.py
etherchainpy/conversions.py
etherchainpy/etherchainpy.py
etherchainpy/geth.py
etherchainpy/logs.py
etherchainpy/transactions.py
EtherChainPy-1.0.80.dist-info/LICENSE
EtherChainPy-1.0.80.dist-info/METADATA
EtherChainPy-1.0.80.dist-info/WHEEL
EtherChainPy-1.0.80.dist-info/top_level.txt
EtherChainPy-1.0.80.dist-info/RECORD
