Metadata-Version: 2.1
Name: EtherChainPy
Version: 1.0.80
Summary: A python interface to the ethereum blockchain explorer at https://www.etherscan.io/apis
Home-page: https://github.com/ZignalNET/EtherChainPy
Author: Emmanuel Adigun
Author-email: emmanuel@zignal.net
Classifier: Programming Language :: Python :: 3
Classifier: License :: OSI Approved :: MIT License
Classifier: Operating System :: OS Independent
License-File: LICENSE
